atomphys/__init__.py
atomphys/atom.py
atomphys/constants.py
atomphys/laser.py
atomphys/state.py
atomphys/term.py
atomphys/transition.py
atomphys/util.py
atomphys/calc/__init__.py
atomphys/calc/polarizability.py
atomphys/calc/wigner.py
atomphys/data/PeriodicTableJSON.json
atomphys/data/__init__.py
atomphys/data/nist.py
tests/__init__.py
tests/conftest.py
tests/test_ASD_import.py
tests/test_Rb.py
tests/test_atom.py
tests/test_states.py
tests/test_term.py
tests/test_util.py
tests/test_wigner.py
atomphys-0.0.4.dist-info/AUTHORS
atomphys-0.0.4.dist-info/LICENSE
atomphys-0.0.4.dist-info/METADATA
atomphys-0.0.4.dist-info/WHEEL
atomphys-0.0.4.dist-info/top_level.txt
atomphys-0.0.4.dist-info/RECORD
