Metadata-Version: 2.1
Name: atomphys
Version: 0.0.4
Summary: Atomic Physics for Python
Home-page: https://github.com/mgrau/atomphys,
Author: "Matt Grau"
Author-email: "matt.grau@gmail.com"
License: MIT,
Project-URL: Bug Tracker, https://github.com/mgrau/atomphys/issues
Keywords: AMO,atomic physics
Platform: UNKNOWN
Classifier: Development Status :: 3 - Alpha
Classifier: Intended Audience :: Science/Research
Classifier: Topic :: Scientific/Engineering :: Physics
Classifier: License :: OSI Approved :: MIT License
Classifier: Programming Language :: Python :: 3.6
Classifier: Programming Language :: Python :: 3.7
Classifier: Programming Language :: Python :: 3.8
Classifier: Programming Language :: Python :: 3.9
Requires-Dist: pint
